simutils/__init__.py
simutils-0.0.2.dist-info/LICENSE
simutils-0.0.2.dist-info/METADATA
simutils-0.0.2.dist-info/WHEEL
simutils-0.0.2.dist-info/top_level.txt
simutils-0.0.2.dist-info/RECORD
