Metadata-Version: 2.1
Name: simutils
Version: 0.0.2
Summary: Tools for logging simulation information for later reproductions.
Home-page: https://github.com/shunichironomura/simutils
Author: Shunichiro Nomura
Author-email: nomura@space.t.u-tokyo.ac.jp
License: MIT
Download-URL: https://github.com/shunichironomura/simutils/archive/v0.0.2.tar.gz
Platform: UNKNOWN
Classifier: Development Status :: 1 - Planning
Classifier: Intended Audience :: Science/Research
Classifier: License :: OSI Approved :: MIT License
Classifier: Programming Language :: Python :: 3
Classifier: Programming Language :: Python :: 3.8
